ebayoauthclient/EbayOAuthClient.py
ebayoauthclient/__init__.py
ebayoauthclient/credentialutil.py
ebayoauthclient/eBayOAuthClient.py
ebayoauthclient/oauth2api.py
ebayoauthclient/model/__init__.py
ebayoauthclient/model/model.py
ebayoauthclient/model/util.py
ebayoauthclient-0.0.3.dist-info/LICENSE
ebayoauthclient-0.0.3.dist-info/METADATA
ebayoauthclient-0.0.3.dist-info/WHEEL
ebayoauthclient-0.0.3.dist-info/top_level.txt
ebayoauthclient-0.0.3.dist-info/RECORD
